{"id":"85FFC764-1F2D-45C6-9428-E723B38902B8","validationEntity":{"analysedDataType":"auto","dataResult":{"createdDate":"2021-12-22T01:03:35Z"}},"modelEntity":{"createdDate":"2021-12-22T01:02:16Z","id":"1CDA9342-9B14-4CD9-BDFB-10401977FE85","experimentID":"85FFC764-1F2D-45C6-9428-E723B38902B8","title":"","modifiedDate":"2021-12-22T01:02:16Z","preferredFilename":"","version":"1.0","modelURL":"Models\/BetterRest%201.mlmodel"},"version":"1.0","settingEntity":{"augmentations":[],"suggestedColumns":["wake","estimatedSleep","coffee","actualSleep"],"targetColumn":"actualSleep","seedType":"default","transferLearningEmbeddingType":"dynamic","handPoseClassifierAugmentations":[],"featureNames":["wake","estimatedSleep","coffee"],"algorithmType":"maxEnt","harVideoAugmentations":0,"taskType":"generalRegresor","suggestedColumnValues":["31,500, 32,400, 26,100, 40,500, 19,800, 27,000, 20,700, 21,600, 41,400, 34,200, 21,600, 78,300, 32,400, 28,800, 18,900, 18,000, 28,800, 18,000, 7,200, 35,100, 24,300, 35,100, 34,200, 27,900, 30,600, 69,300, 35,100, 34,200, 34,200, 23,400","9.00, 5.00, 6.50, 8.75, 6.00, 7.50, 9.25, 6.00, 9.25, 6.75, 5.25, 9.25, 10.00, 8.75, 8.25, 6.25, 10.00, 6.25, 10.00, 9.50, 5.00, 7.50, 6.25, 8.00, 8.00, 6.50, 8.00, 10.00, 8.25, 8.00","6, 2, 10, 4, 3, 1, 1, 3, 5, 8, 3, 8, 2, 3, 1, 2, 3, 2, 1, 4, 2, 1, 1, 4, 3, 7, 4, 4, 1, 3","38,230, 20,180, 31,989, 35,258, 24,487, 28,300, 34,548, 24,557, 37,836, 31,340, 21,874, 40,405, 38,076, 34,265, 30,936, 24,665, 39,007, 24,578, 37,267, 37,878, 20,220, 28,400, 23,882, 32,427, 31,699, 29,670, 32,789, 39,792, 30,935, 31,701"],"handActionClassifierAugmentations":[],"suggestedColumnTypes":["Int","Double","Int","Int"],"styleTransferAlgorithmType":"image","generalRegressorType":{"auto":{}}},"state":"trained","trainingEntity":{"finishTime":"2021-12-22T01:07:32Z","recipeTrainingResults":{"generalRegressor":{"maximumError":700.52805131514469,"rootMeanSquaredError":177.21237611415248}},"dataResult":{"itemsCount":10000,"createdDate":"2021-12-22T01:03:35Z","dataURL":"file:\/\/\/Users\/braydenlemke\/Desktop\/projects\/HackingWithSwift\/SwiftUI\/project4-files\/BetterRest.csv","columnTypes":["Int","Double","Int","Int"],"analysis":{"summary":{"sampleCount":10000,"canUseValidation":1},"issues":[{"description":"Data has 10000 rows","severity":"info"}],"regressorAnalysis":{"targetRange":[19216,45224]}},"dataSourceID":"3BCB14D7-38AE-4EF7-B097-75F1E8CD808E","columns":["wake","estimatedSleep","coffee","actualSleep"],"columnValues":["31,500, 32,400, 26,100, 40,500, 19,800, 27,000, 20,700, 21,600, 41,400, 34,200, 21,600, 78,300, 32,400, 28,800, 18,900, 18,000, 28,800, 18,000, 7,200, 35,100, 24,300, 35,100, 34,200, 27,900, 30,600, 69,300, 35,100, 34,200, 34,200, 23,400","9.00, 5.00, 6.50, 8.75, 6.00, 7.50, 9.25, 6.00, 9.25, 6.75, 5.25, 9.25, 10.00, 8.75, 8.25, 6.25, 10.00, 6.25, 10.00, 9.50, 5.00, 7.50, 6.25, 8.00, 8.00, 6.50, 8.00, 10.00, 8.25, 8.00","6, 2, 10, 4, 3, 1, 1, 3, 5, 8, 3, 8, 2, 3, 1, 2, 3, 2, 1, 4, 2, 1, 1, 4, 3, 7, 4, 4, 1, 3","38,230, 20,180, 31,989, 35,258, 24,487, 28,300, 34,548, 24,557, 37,836, 31,340, 21,874, 40,405, 38,076, 34,265, 30,936, 24,665, 39,007, 24,578, 37,267, 37,878, 20,220, 28,400, 23,882, 32,427, 31,699, 29,670, 32,789, 39,792, 30,935, 31,701"],"targetRange":[19216,45224]},"dataURL":"file:\/\/\/Users\/braydenlemke\/Desktop\/projects\/HackingWithSwift\/SwiftUI\/project4-files\/BetterRest.csv","featureExtractionCheckpointMayBeAvailable":false,"recipeValidationResults":{"generalRegressor":{"maximumError":694.01673825963371,"rootMeanSquaredError":173.8227604841606}},"progress":[],"trainingAccuracy":177.21237611415248,"checkpointMetrics":{},"analysedDataType":"none","dataSourceID":"3BCB14D7-38AE-4EF7-B097-75F1E8CD808E","snapshottableCheckpoints":{},"validationAccuracy":173.8227604841606,"startTime":"2021-12-22T01:07:31Z"},"createdDate":"2021-12-22T01:02:16Z","evaluationContainerEntity":{"testingEvaluationEntity":{"id":"e09ffaa2-38fc-444f-a466-31b1cab01e57","createdDate":"2021-12-22T01:02:16Z","dataResult":{"createdDate":"2021-12-22T01:03:35Z"},"analysedDataType":"none"},"createdDate":"2021-12-22T01:07:44Z","id":"cef546e9-d043-436c-ad50-f9eb82dd98e5","trainingEvaluationEntity":{"result":{"generalRegressor":{"maximumError":700.52805131514469,"rootMeanSquaredError":177.21237611415248}},"createdDate":"2021-12-22T01:02:16Z","id":"f9909c4d-2c52-40cb-a366-b9554f9674f0","dataURL":"file:\/\/\/Users\/braydenlemke\/Desktop\/projects\/HackingWithSwift\/SwiftUI\/project4-files\/BetterRest.csv","dataSourceID":"3BCB14D7-38AE-4EF7-B097-75F1E8CD808E","dataResult":{"itemsCount":10000,"createdDate":"2021-12-22T01:03:35Z","targetRange":[19216,45224],"dataURL":"file:\/\/\/Users\/braydenlemke\/Desktop\/projects\/HackingWithSwift\/SwiftUI\/project4-files\/BetterRest.csv","dataSourceID":"3BCB14D7-38AE-4EF7-B097-75F1E8CD808E","analysis":{"summary":{"sampleCount":10000,"canUseValidation":1},"issues":[{"description":"Data has 10000 rows","severity":"info"}],"regressorAnalysis":{"targetRange":[19216,45224]}}},"analysedDataType":"none"},"previewType":"tabularRegressor","modifiedDate":"2021-12-22T01:07:44Z","validationEvaluationEntity":{"result":{"generalRegressor":{"maximumError":694.01673825963371,"rootMeanSquaredError":173.8227604841606}},"id":"7350b075-f437-401c-8220-1406660dc435","createdDate":"2021-12-22T01:02:16Z","dataResult":{"createdDate":"2021-12-22T01:03:35Z"},"analysedDataType":"auto"},"evaluationEntities":[{"id":"ec6b2af1-fb09-4314-b5c4-1922a3386522","createdDate":"2021-12-22T01:07:44Z","dataResult":{},"analysedDataType":"none"}]},"evaluationEntities":[],"activityEntities":["trainingStarted",[{"id":"30859BCE-675B-4F4C-82C5-0B2DA8C1BB56","title":"Training Started","createdDate":"2021-12-22T01:07:31Z","event":"trainingStarted","subtitle":"BetterRest 1"}],"experimentCreated",[{"id":"DD671C9B-5D4F-4F33-8D48-4E4239A03B27","title":"Model Source Created","createdDate":"2021-12-22T01:02:16Z","event":"experimentCreated","subtitle":"BetterRest 1"}],"trainingDataAdded",[{"id":"EEF2DC08-D7DA-4ED4-A977-828D5799C739","title":"Training Data Added","createdDate":"2021-12-22T01:03:35Z","event":"trainingDataAdded","subtitle":"BetterRest.csv"}],"trainingFinished",[{"id":"765550DC-FC25-46AD-AFAA-B437C8AB2688","title":"Training Completed","createdDate":"2021-12-22T01:07:32Z","event":"trainingFinished","subtitle":"BetterRest 1"}]],"title":"BetterRest 1","evaluationEntity":{"id":"03d5144b-32e0-4d76-b2a1-88db1a527371","createdDate":"2021-12-22T01:02:16Z","dataResult":{"createdDate":"2021-12-22T01:03:35Z"},"analysedDataType":"none"},"evaluationState":"uninitialized","snapshotRole":{"withoutSnapshots":0},"modifiedDate":"2021-12-22T01:07:44Z","contentDataResult":{"createdDate":"2021-12-22T01:03:35Z"},"preferredFilename":"BetterRest 1"}